README.md
package_info.json
setup.py
th2_grpc_crawler_check2/__init__.py
th2_grpc_crawler_check2/check2_service.py
th2_grpc_crawler_check2/crawler_check2.proto
th2_grpc_crawler_check2/crawler_check2_pb2.py
th2_grpc_crawler_check2/crawler_check2_pb2_grpc.py
th2_grpc_crawler_check2.egg-info/PKG-INFO
th2_grpc_crawler_check2.egg-info/SOURCES.txt
th2_grpc_crawler_check2.egg-info/dependency_links.txt
th2_grpc_crawler_check2.egg-info/requires.txt
th2_grpc_crawler_check2.egg-info/top_level.txt