Metadata-Version: 2.1
Name: th2-grpc-crawler-check2
Version: 0.0.1.dev949460457
Summary: th2_grpc_crawler_check2
Home-page: https://github.com/th2-net/th2-grpc-crawler-check2
Author: TH2-devs
Author-email: th2-devs@exactprosystems.com
License: Apache License 2.0
Platform: UNKNOWN
Requires-Python: >=3.7
